po2xls/__init__.py
po2xls/apps.py
po2xls/converters.py
po2xls/exceptions.py
po2xls/locale/en/LC_MESSAGES/django.mo
po2xls/locale/en/LC_MESSAGES/django.po
po2xls/locale/uk/LC_MESSAGES/django.mo
po2xls/locale/uk/LC_MESSAGES/django.po
po2xls/management/__init__.py
po2xls/management/commands/__init__.py
po2xls/management/commands/po-to-xls.py
django_po2xls-0.11.2.dist-info/COPYING
django_po2xls-0.11.2.dist-info/METADATA
django_po2xls-0.11.2.dist-info/WHEEL
django_po2xls-0.11.2.dist-info/top_level.txt
django_po2xls-0.11.2.dist-info/RECORD
