Metadata-Version: 2.1
Name: django-po2xls
Version: 0.11.2
Summary: Convert gettext .po files to .xls
Home-page: https://github.com/vint21h/django-po2xls/
Author: Alexei Andrushievich
Author-email: vint21h@vint21h.pp.ua
License: GPLv3+
Keywords: django,xls,po,xls2po,converter
Platform: UNKNOWN
Classifier: Development Status :: 5 - Production/Stable
Classifier: Environment :: Console
Classifier: Environment :: Plugins
Classifier: Framework :: Django :: 2.2
Classifier: Framework :: Django :: 3.0
Classifier: Framework :: Django :: 3.1
Classifier: Framework :: Django :: 3.2
Classifier: License :: OSI Approved :: GNU General Public License v3 or later (GPLv3+)
Classifier: Operating System :: Unix
Classifier: Programming Language :: Python :: 3.6
Classifier: Programming Language :: Python :: 3.7
Classifier: Programming Language :: Python :: 3.8
Classifier: Programming Language :: Python :: 3.9
Classifier: Programming Language :: Python :: 3.10
Classifier: Topic :: Utilities
Requires-Dist: django-appconf (>=1.0.3)
Requires-Dist: django-rosetta (>=0.9.3)
Requires-Dist: django (<4.0,>=2.2)
Requires-Dist: polib (>=1.1.0)
Requires-Dist: xlwt (>=1.3.0)
Provides-Extra: test
Requires-Dist: attrs (==21.2.0) ; extra == 'test'
Requires-Dist: bandit (==1.7.1) ; extra == 'test'
Requires-Dist: black (==21.10b0) ; extra == 'test'
Requires-Dist: bpython (==0.22.1) ; extra == 'test'
Requires-Dist: check-manifest (==0.47) ; extra == 'test'
Requires-Dist: check-wheel-contents (==0.3.3) ; extra == 'test'
Requires-Dist: coverage (==6.1.2) ; extra == 'test'
Requires-Dist: coveralls (==3.3.1) ; extra == 'test'
Requires-Dist: curlylint (==0.13.0) ; extra == 'test'
Requires-Dist: darglint (==1.8.1) ; extra == 'test'
Requires-Dist: dennis (==0.9) ; extra == 'test'
Requires-Dist: django-stubs (==1.9.0) ; extra == 'test'
Requires-Dist: dlint (==0.12.0) ; extra == 'test'
Requires-Dist: dodgy (==0.2.1) ; extra == 'test'
Requires-Dist: dotenv-linter (==0.2.0) ; extra == 'test'
Requires-Dist: flake8-annotations-complexity (==0.0.6) ; extra == 'test'
Requires-Dist: flake8-annotations-coverage (==0.0.5) ; extra == 'test'
Requires-Dist: flake8-broken-line (==0.4.0) ; extra == 'test'
Requires-Dist: flake8-bugbear (==21.9.2) ; extra == 'test'
Requires-Dist: flake8-builtins (==1.5.3) ; extra == 'test'
Requires-Dist: flake8-coding (==1.3.2) ; extra == 'test'
Requires-Dist: flake8-cognitive-complexity (==0.1.0) ; extra == 'test'
Requires-Dist: flake8-comprehensions (==3.7.0) ; extra == 'test'
Requires-Dist: flake8-debugger (==4.0.0) ; extra == 'test'
Requires-Dist: flake8-django (==1.1.2) ; extra == 'test'
Requires-Dist: flake8-docstrings (==1.6.0) ; extra == 'test'
Requires-Dist: flake8-eradicate (==1.2.0) ; extra == 'test'
Requires-Dist: flake8-executable (==2.1.1) ; extra == 'test'
Requires-Dist: flake8-expression-complexity (==0.0.9) ; extra == 'test'
Requires-Dist: flake8-fixme (==1.1.1) ; extra == 'test'
Requires-Dist: flake8-functions (==0.0.6) ; extra == 'test'
Requires-Dist: flake8-mutable (==1.2.0) ; extra == 'test'
Requires-Dist: flake8-print (==4.0.0) ; extra == 'test'
Requires-Dist: flake8-return (==1.1.3) ; extra == 'test'
Requires-Dist: flake8-simplify (==0.14.2) ; extra == 'test'
Requires-Dist: flake8-typing-imports (==1.11.0) ; extra == 'test'
Requires-Dist: flake8-use-fstring (==1.3) ; extra == 'test'
Requires-Dist: flake8-variables-names (==0.0.4) ; extra == 'test'
Requires-Dist: flake8 (==3.9.2) ; extra == 'test'
Requires-Dist: importlib-metadata (==4.8.2) ; extra == 'test'
Requires-Dist: interrogate (==1.5.0) ; extra == 'test'
Requires-Dist: isort (==5.10.1) ; extra == 'test'
Requires-Dist: mypy (==0.910) ; extra == 'test'
Requires-Dist: pep8-naming (==0.12.1) ; extra == 'test'
Requires-Dist: pip-outdated (==0.4.0) ; extra == 'test'
Requires-Dist: polint (==0.4) ; extra == 'test'
Requires-Dist: pre-commit-hooks (==4.0.1) ; extra == 'test'
Requires-Dist: pre-commit (==2.15.0) ; extra == 'test'
Requires-Dist: pygments (==2.10.0) ; extra == 'test'
Requires-Dist: pylint-django (==2.4.4) ; extra == 'test'
Requires-Dist: pylint (==2.11.1) ; extra == 'test'
Requires-Dist: pyroma (==3.2) ; extra == 'test'
Requires-Dist: pytest-cov (==3.0.0) ; extra == 'test'
Requires-Dist: pytest-django (==4.4.0) ; extra == 'test'
Requires-Dist: pytest-extra-durations (==0.1.3) ; extra == 'test'
Requires-Dist: pytest-instafail (==0.4.2) ; extra == 'test'
Requires-Dist: pytest-sugar (==0.9.4) ; extra == 'test'
Requires-Dist: pytest-timer[termcolor] (==0.0.11) ; extra == 'test'
Requires-Dist: pytest (==6.2.5) ; extra == 'test'
Requires-Dist: readme-renderer (==30.0) ; extra == 'test'
Requires-Dist: removestar (==1.3.1) ; extra == 'test'
Requires-Dist: seed-isort-config (==2.2.0) ; extra == 'test'
Requires-Dist: tabulate (==0.8.9) ; extra == 'test'
Requires-Dist: tox-gh-actions (==2.8.1) ; extra == 'test'
Requires-Dist: tox-pyenv (==1.1.0) ; extra == 'test'
Requires-Dist: tox (==3.24.4) ; extra == 'test'
Requires-Dist: twine (==3.6.0) ; extra == 'test'
Requires-Dist: types-polib (==1.1.5) ; extra == 'test'
Requires-Dist: wheel (==0.37.0) ; extra == 'test'
Requires-Dist: xlrd (==2.0.1) ; extra == 'test'
Requires-Dist: yesqa (==1.3.0) ; extra == 'test'
